sciutil/__init__.py
sciutil/__main__.py
sciutil/biomart.py
sciutil/msg.py
sciutil/util.py
sciutil-1.0.3.data/data/LICENSE
sciutil-1.0.3.dist-info/LICENSE
sciutil-1.0.3.dist-info/METADATA
sciutil-1.0.3.dist-info/WHEEL
sciutil-1.0.3.dist-info/entry_points.txt
sciutil-1.0.3.dist-info/top_level.txt
sciutil-1.0.3.dist-info/RECORD
