Metadata-Version: 2.1
Name: sciutil
Version: 1.0.3
Summary: Utility functions for the sci* packages.
Home-page: https://github.com/ArianeMora/sciutil
Author: Ariane Mora
Author-email: ariane.mora@uq.net.au
License: GPL3
Project-URL: Bug Tracker, https://github.com/ArianeMora/sciutil/issues
Project-URL: Documentation, https://github.com/ArianeMora/sciutil
Project-URL: Source Code, https://github.com/ArianeMora/sciutil
Keywords: util
Platform: UNKNOWN
Classifier: Development Status :: 5 - Production/Stable
Classifier: Intended Audience :: Science/Research
Classifier: License :: OSI Approved :: GNU General Public License v3 (GPLv3)
Classifier: Natural Language :: English
Classifier: Operating System :: OS Independent
Classifier: Programming Language :: Python :: 3.6
Classifier: Programming Language :: Python :: 3.7
Classifier: Programming Language :: Python :: 3.8
Classifier: Topic :: Scientific/Engineering :: Bio-Informatics
Requires-Python: >=3.6
